soco_device/GPUtil.py
soco_device/__init__.py
soco_device/device_check.py
soco_device-0.0.5.2.dist-info/LICENSE
soco_device-0.0.5.2.dist-info/METADATA
soco_device-0.0.5.2.dist-info/WHEEL
soco_device-0.0.5.2.dist-info/top_level.txt
soco_device-0.0.5.2.dist-info/RECORD
