Metadata-Version: 2.1
Name: soco-device
Version: 0.0.5.2
Summary: Log memory usage and auto choose device for machine learning model inference
Home-page: https://www.soco.ai
Author: xiaopeng lu
License: UNKNOWN
Platform: UNKNOWN
Classifier: Programming Language :: Python :: 3
Classifier: License :: Free for non-commercial use
Classifier: Operating System :: OS Independent
